CHANGELOG.txt
LICENSE.txt
MANIFEST.in
README.txt
setup.py
khengool/__init__.py
khengool.egg-info/PKG-INFO
khengool.egg-info/SOURCES.txt
khengool.egg-info/dependency_links.txt
khengool.egg-info/top_level.txt