Metadata-Version: 2.1
Name: khengool
Version: 0.0.1
Summary: This is a simple module for very dumb kids in 8/3 class in Alame Helli1
Home-page: UNKNOWN
Author: Shayan Azizi
Author-email: shayanazizi1386@gmail.com
License: MIT
Keywords: khengool
Platform: UNKNOWN
Classifier: Development Status :: 5 - Production/Stable
Classifier: Intended Audience :: Education
Classifier: Operating System :: Microsoft :: Windows :: Windows 10
Classifier: License :: OSI Approved :: MIT License
Classifier: Programming Language :: Python :: 3
License-File: LICENSE.txt
